_matrix_hal_nfc.cpython-35m-arm-linux-gnueabihf.so
matrix_lite_nfc/__init__.py
matrix_lite_nfc/read.py
matrix_lite_nfc-0.0.2.dist-info/METADATA
matrix_lite_nfc-0.0.2.dist-info/WHEEL
matrix_lite_nfc-0.0.2.dist-info/top_level.txt
matrix_lite_nfc-0.0.2.dist-info/RECORD
