Metadata-Version: 2.1
Name: matrix-lite-nfc
Version: 0.0.2
Summary: A Python wrapper for MATRIX HAL NFC
Home-page: https://github.com/matrix-io/matrix-lite-nfc-py
Author: MATRIX
Author-email: devel@matrixlabs.ai
License: UNKNOWN
Platform: UNKNOWN
Classifier: Programming Language :: Python :: 3.5
Classifier: Programming Language :: Python :: 3.7
